odoo/addons/website_event_sale_hide_ticket/README.rst
odoo/addons/website_event_sale_hide_ticket/__init__.py
odoo/addons/website_event_sale_hide_ticket/__manifest__.py
odoo/addons/website_event_sale_hide_ticket/i18n/it.po
odoo/addons/website_event_sale_hide_ticket/i18n/website_event_sale_hide_ticket.pot
odoo/addons/website_event_sale_hide_ticket/models/__init__.py
odoo/addons/website_event_sale_hide_ticket/models/event_event.py
odoo/addons/website_event_sale_hide_ticket/models/event_ticket.py
odoo/addons/website_event_sale_hide_ticket/readme/CONFIGURE.rst
odoo/addons/website_event_sale_hide_ticket/readme/CONTRIBUTORS.rst
odoo/addons/website_event_sale_hide_ticket/readme/DESCRIPTION.rst
odoo/addons/website_event_sale_hide_ticket/static/description/icon.png
odoo/addons/website_event_sale_hide_ticket/static/description/index.html
odoo/addons/website_event_sale_hide_ticket/templates/event_ticket.xml
odoo/addons/website_event_sale_hide_ticket/views/event_ticket.xml
odoo13_addon_website_event_sale_hide_ticket-13.0.1.0.1.dev6.dist-info/METADATA
odoo13_addon_website_event_sale_hide_ticket-13.0.1.0.1.dev6.dist-info/WHEEL
odoo13_addon_website_event_sale_hide_ticket-13.0.1.0.1.dev6.dist-info/top_level.txt
odoo13_addon_website_event_sale_hide_ticket-13.0.1.0.1.dev6.dist-info/RECORD
