Metadata-Version: 2.1
Name: odoo13-addon-website-event-sale-hide-ticket
Version: 13.0.1.0.1.dev6
Summary: Allow to hide event ticket from the website
Home-page: https://github.com/OCA/event
Author: Camptocamp, Odoo Community Association (OCA)
Author-email: support@odoo-community.org
License: AGPL-3
Platform: UNKNOWN
Classifier: Programming Language :: Python
Classifier: Framework :: Odoo
Classifier: Framework :: Odoo :: 13.0
Classifier: License :: OSI Approved :: GNU Affero General Public License v3
Classifier: Development Status :: 4 - Beta
Requires-Python: >=3.5
Requires-Dist: odoo <13.1dev,>=13.0a
